django_highcharts_series.py
django_highcharts_series-0.0.1.dist-info/LICENSE.txt
django_highcharts_series-0.0.1.dist-info/METADATA
django_highcharts_series-0.0.1.dist-info/WHEEL
django_highcharts_series-0.0.1.dist-info/top_level.txt
django_highcharts_series-0.0.1.dist-info/RECORD
