Metadata-Version: 2.1
Name: django-highcharts-series
Version: 0.0.1
Summary: HighCharts Creation for django models
Home-page: https://github.com/NamitPandey/PythonPackage/tree/master/Django_HighCharts
Author: NightOwlMorningPanda
Author-email: nightowlmorningpanda@gmail.com
License: UNKNOWN
Platform: UNKNOWN
Classifier: Programming Language :: Python :: 3
Classifier: Programming Language :: Python :: 3.8
Classifier: License :: OSI Approved :: MIT License
Classifier: Operating System :: OS Independent
Requires-Python: >=3.7
